rexi/__init__.py
rexi/cli.py
rexi/regex_help.py
rexi/rexi.py
rexi/rexi.tcss
rexi-1.2.0.dist-info/LICENSE
rexi-1.2.0.dist-info/METADATA
rexi-1.2.0.dist-info/WHEEL
rexi-1.2.0.dist-info/entry_points.txt
rexi-1.2.0.dist-info/RECORD
