Metadata-Version: 2.1
Name: rexi
Version: 1.2.0
Summary: Simpel and Interactive regex shell
Home-page: https://github.com/royreznik/rexi
Author: Roy Reznik
Author-email: royreznik@gmail.com
Requires-Python: >=3.10,<4.0
Classifier: License :: OSI Approved :: MIT License
Classifier: Programming Language :: Python :: 3
Classifier: Programming Language :: Python :: 3.10
Classifier: Programming Language :: Python :: 3.11
Classifier: Programming Language :: Python :: 3.12
Classifier: Programming Language :: Python :: 3.8
Classifier: Programming Language :: Python :: 3.9
Requires-Dist: colorama (>=0.4.6,<0.5.0)
Requires-Dist: textual (>=0.52.1,<0.53.0)
Requires-Dist: typer (>=0.9.0,<0.10.0)
Project-URL: Repository, https://github.com/royreznik/rexi
